LICENSE
MANIFEST.in
README.rst
setup.py
log4django/__init__.py
log4django/admin.py
log4django/callbacks.py
log4django/context_processors.py
log4django/decorators.py
log4django/formatters.py
log4django/handlers.py
log4django/middleware.py
log4django/models.py
log4django/routers.py
log4django/settings.py
log4django/urls.py
log4django/utils.py
log4django.egg-info/PKG-INFO
log4django.egg-info/SOURCES.txt
log4django.egg-info/dependency_links.txt
log4django.egg-info/requires.txt
log4django.egg-info/top_level.txt
log4django/api/__init__.py
log4django/api/authentication.py
log4django/api/resources.py
log4django/exports/__init__.py
log4django/exports/csv.py
log4django/fixtures/initial_data.xml
log4django/management/__init__.py
log4django/management/commands/__init__.py
log4django/management/commands/log4django.py
log4django/migrations/0001_initial.py
log4django/migrations/0002_auto__add_field_logrecord_request_id.py
log4django/migrations/0003_auto__chg_field_logrecord_app.py
log4django/migrations/__init__.py
log4django/pipeline/__init__.py
log4django/pipeline/authentication.py
log4django/pipeline/process_bundle_data.py
log4django/static/log4django/assets/css/docs.css
log4django/static/log4django/assets/css/pygments-manni.css
log4django/static/log4django/assets/ico/apple-touch-icon-114-precomposed.png
log4django/static/log4django/assets/ico/apple-touch-icon-144-precomposed.png
log4django/static/log4django/assets/ico/apple-touch-icon-57-precomposed.png
log4django/static/log4django/assets/ico/apple-touch-icon-72-precomposed.png
log4django/static/log4django/assets/ico/favicon.png
log4django/static/log4django/assets/js/application.js
log4django/static/log4django/assets/js/customizer.js
log4django/static/log4django/assets/js/filesaver.js
log4django/static/log4django/assets/js/holder.js
log4django/static/log4django/assets/js/html5shiv.js
log4django/static/log4django/assets/js/jquery.js
log4django/static/log4django/assets/js/jszip.js
log4django/static/log4django/assets/js/less.js
log4django/static/log4django/assets/js/raw-files.js
log4django/static/log4django/assets/js/respond.min.js
log4django/static/log4django/assets/js/uglify.js
